odoo8_addon_mgmtsystem_nonconformity_project-8.0.1.0.0-py2.7-nspkg.pth
odoo_addons/mgmtsystem_nonconformity_project/__openerp__.py
odoo_addons/mgmtsystem_nonconformity_project/__init__.py
odoo_addons/mgmtsystem_nonconformity_project/README.rst
odoo_addons/mgmtsystem_nonconformity_project/models/__init__.py
odoo_addons/mgmtsystem_nonconformity_project/models/mgmtsystem_nonconformity_project.py
odoo_addons/mgmtsystem_nonconformity_project/i18n/es.po
odoo_addons/mgmtsystem_nonconformity_project/i18n/hr.po
odoo_addons/mgmtsystem_nonconformity_project/i18n/mgmtsystem_nonconformity_project.pot
odoo_addons/mgmtsystem_nonconformity_project/i18n/sl.po
odoo_addons/mgmtsystem_nonconformity_project/i18n/nb.po
odoo_addons/mgmtsystem_nonconformity_project/i18n/de.po
odoo_addons/mgmtsystem_nonconformity_project/i18n/vi.po
odoo_addons/mgmtsystem_nonconformity_project/i18n/fr.po
odoo_addons/mgmtsystem_nonconformity_project/i18n/pt_BR.po
odoo_addons/mgmtsystem_nonconformity_project/views/mgmtsystem_nonconformity_project.xml
odoo_addons/mgmtsystem_nonconformity_project/data/mgmtsystem_nonconformity_project_data.xml
odoo_addons/mgmtsystem_nonconformity_project/static/description/icon.png
odoo8_addon_mgmtsystem_nonconformity_project-8.0.1.0.0.dist-info/top_level.txt
odoo8_addon_mgmtsystem_nonconformity_project-8.0.1.0.0.dist-info/WHEEL
odoo8_addon_mgmtsystem_nonconformity_project-8.0.1.0.0.dist-info/RECORD
odoo8_addon_mgmtsystem_nonconformity_project-8.0.1.0.0.dist-info/metadata.json
odoo8_addon_mgmtsystem_nonconformity_project-8.0.1.0.0.dist-info/DESCRIPTION.rst
odoo8_addon_mgmtsystem_nonconformity_project-8.0.1.0.0.dist-info/METADATA
odoo8_addon_mgmtsystem_nonconformity_project-8.0.1.0.0.dist-info/namespace_packages.txt
